filigran_sseclient/__init__.py
filigran_sseclient/sseclient.py
filigran_sseclient-1.0.1.dist-info/LICENSE
filigran_sseclient-1.0.1.dist-info/METADATA
filigran_sseclient-1.0.1.dist-info/WHEEL
filigran_sseclient-1.0.1.dist-info/top_level.txt
filigran_sseclient-1.0.1.dist-info/RECORD
